{
	"Ferienjob": 0,
	"illustration": 0,
	"XTRA": 0,
	"OnlyTrump": 0,
	"toyotamr2": 0,
	"StayingAlive": 0,
	"game": 0,
	"AnnaWestinAct": 0,
	"themes": 0,
	"AusenciaIncompleta": 0,
	"QueroNoTVZ": 0,
	"gardens": 0,
	"ReferendumYa": 0,
	"AONEMKTG": 0,
	"ad": 0,
	"TEAMFOLLOWBACK": 0,
	"Art": 0,
	"izmir": 0,
	"HTML": 0,
	"Irumugan": 0,
	"Beadnell": 0,
	"TFB": 0,
	"personasdecarton": 0,
	"OuiÇaVaMieux": 0,
	"TipsHands": 0,
	"Room": 0,
	"chrysler100": 0,
	"MohammadAbbas": 0,
	"Esmeraldas": 0,
	"momlife": 0,
	"PowerGirl": 0,
	"SHSUDerbyDays2k16": 0,
	"sigmachi": 0,
	"DFWBloggers": 0,
	"RhymenNoodles": 0,
	"pnw": 0,
	"plantbased": 0,
	"Seattle": 0,
	"TweetMe": 0,
	"WeekendAdventures": 0,
	"universitychallenge": 0,
	"Pic": 0,
	"playas": 0,
	"gym": 0,
	"EGU16": 0,
	"FrasesGeniales": 0,
	"lovemypharmacy": 0,
	"goodafternoon": 0,
	"sherwoodhour": 0,
	"WFMloveslocal": 0,
	"CFCU19": 0,
	"JurassicPark": 0,
	"PanamaPapers": 0,
	"EstoyConElla": 0,
	"ParticiparEsTransformar": 0,
	"VCTE64": 0,
	"ChildSoldiers": 0,
	"neoconservative": 0,
	"Poncitlán": 0,
	"Elmer": 0,
	"SierraLeone": 0,
	"saudi": 0,
	"Watchout": 0,
	"win": 0,
	"MDPrimary": 0,
	"YL": 0,
	"ATATÜRK": 0,
	"Photo": 0,
	"Tijuana": 0,
	"competition": 0,
	"ElLobo": 0,
	"racerxfab": 0,
	"Geral": 0,
	"nayanthara": 0,
	"FreeNnamdiKanu": 0,
	"CTCAMéxico": 0,
	"cnn": 0,
	"VivaLaManana": 0,
	"norfolkhour": 0,
	"MGWV": 0,
	"StopBashing": 0,
	"Swaziland": 0,
	"BlackberryClassic": 0,
	"DarthVader": 0,
	"TyrantBuhari": 0,
	"punish": 0,
	"RamatRachel": 0,
	"MAD": 0,
	"Quran": 0,
	"Caps": 0,
	"WATS2016": 0,
	"kcnv": 0,
	"SoundCloud": 0,
	"AEGEEday": 0,
	"vod": 0,
	"UNAMalDía": 0,
	"FirstDates": 0,
	"Hookah": 0,
	"NameYourFavoriteSong": 0,
	"Mexicali": 0,
	"GrandBanditisme": 0,
	"landscaping": 0,
	"Joker": 0,
	"DalkurdFF": 0,
	"Mataró": 0,
	"JosemaYPauPedimosAMicaEnEEES": 0,
	"MacriSA": 0,
	"DontMancriminate": 0,
	"avanttic_jobs": 0,
	"ClownTrain": 0,
	"JBG": 0,
	"Somalia": 0,
	"Venezuela": 0,
	"SpringHasSprung": 0,
	"PointLoma": 0,
	"Weed": 0,
	"V": 0,
	"ElDosierDelRey": 0,
	"Technology": 0,
	"GoodMusic": 0,
	"EADT577": 0,
	"içindekisen": 0,
	"quote": 0,
	"Gratis": 0,
	"econarchive": 0,
	"BoaTarde": 0,
	"eastenders": 0,
	"Schwäbisch": 0,
	"StarWars": 0,
	"Indianapolis": 0,
	"HondaCivicTour": 0,
	"fyseo_ru": 0,
	"Miifoto": 0,
	"Dank": 0,
	"AppreciationTweet": 0,
	"Bansha": 0,
	"ChicagoFire": 0,
	"Tebuscamos": 0,
	"nets": 0,
	"JFB": 0,
	"Witch": 0,
	"AAP": 0,
	"cumsluts": 0,
	"Guayaquil": 0,
	"ClexaFF": 0,
	"TakeMeToTheOcean": 0,
	"bhive": 0,
	"Mauro": 0,
	"ItsTime": 0,
	"renovation": 0,
	"Veestro": 0,
	"TheSocialHrRadio": 0,
	"wpfruits": 0,
	"issabove": 0,
	"norfolkjob": 0,
	"JB": 0,
	"agTheatreVille": 0,
	"Nland": 0,
	"Miitomo": 0,
	"Marla": 0,
	"ksa": 0,
	"begaythai": 0,
	"keepitsocial": 0,
	"news": 0,
	"RS": 0,
	"datingadvice": 0,
	"NoLoHagas": 0,
	"David2016": 0,
	"ru": 0,
	"MIssão": 0,
	"adana": 0,
	"HarryPotterPlay": 0,
	"OneTreeHill": 0,
	"miradormundial": 0,
	"umRei": 0,
	"inspiration": 0,
	"TheseCandidatesIn4Words": 0,
	"carousell": 0,
	"Giveaway": 0,
	"BeTheDifference": 0,
	"SismoEcuador": 0,
	"M5S": 0,
	"oikeusääneen": 0,
	"YoungK": 0,
	"MêmeLesMoches": 0,
	"laureusawards": 0,
	"MervynKing": 0,
	"Balance": 0,
	"lvphil": 0,
	"SCFCvTHFC": 0,
	"todayschilis": 0,
	"wordpress": 0,
	"buenastardes": 0,
	"womeninbusiness": 0,
	"featurewall": 0,
	"Cruz": 0,
	"trucking": 0,
	"TheSummit16": 0,
	"CursoBásico": 0,
	"Videos": 0,
	"CrestaRoja": 0,
	"toughviking": 0,
	"Motivacion": 0,
	"BBClassic": 0,
	"HairMusicVideo": 0,
	"Escorpio": 0,
	"toystory": 0,
	"BetterTogether": 0,
	"Pot": 0,
	"blake2": 0,
	"MLM": 0,
	"stills": 0,
	"ACUARIO": 0,
	"twitterchampion": 0,
	"MarkBam": 0,
	"CAPrimary": 0,
	"Juarez": 0,
	"TragediaWarp": 0,
	"teenporn": 0,
	"exhaust": 0,
	"EP02": 0,
	"ROCA12": 0,
	"northeasthour": 0,
	"i386PC": 0,
	"musicmonday": 0,
	"eastmidshour": 0,
	"Mbombo_byVeeckokyngz": 0,
	"AvisoMetro": 0,
	"OptimumCommunity": 0,
	"LucaMarinelli": 0,
	"lufc": 0,
	"teacherproblems": 0,
	"homedecor": 0,
	"MM": 0,
	"training": 0,
	"Escorpião": 0,
	"beer": 0,
	"IlseJacobsen": 0,
	"gamedev": 0,
	"pasajeSeguro": 0,
	"Che": 0,
	"yeahok": 0,
	"karadayiLaVisita": 0,
	"JUNGKOOK": 0,
	"LinuxRules": 0,
	"infographic": 0,
	"DerrenMiracle": 0,
	"Python": 0,
	"design": 0,
	"NC": 0,
	"temporadadecalor": 0,
	"concert": 0,
	"Superettan": 0,
	"DreamTeam": 0,
	"Iraq": 0,
	"Amici15": 0,
	"Tucacas": 0,
	"mr2": 0,
	"Sagittarius": 0,
	"Notícias": 0,
	"ff": 0,
	"twitterafterdark": 0,
	"DueleElCorazon": 0,
	"AutoFollow": 0,
	"Chihuahua": 0,
	"BuddhaLovers": 0,
	"interiordesign": 0,
	"HarleyQuinn": 0,
	"tubabuyukustun": 0,
	"PremierLeague": 0,
	"GainWithKOT": 0,
	"BurnTheGOPDown": 0,
	"Jalisco": 0,
	"gardening": 0,
	"proud": 0,
	"livingwater": 0,
	"chess": 0,
	"LGRW": 0,
	"JavaScript": 0,
	"HissederekSöylüyorum": 0,
	"Win": 0,
	"GoFH2017": 0,
	"PiazzaPulita": 0,
	"home": 0,
	"CampLionMaker": 0,
	"ItsTimeForChange": 0,
	"LFC": 0,
	"Refugees": 0,
	"ru_ff": 0,
	"Charlotte": 0,
	"yosobrevivialsanjorge": 0,
	"3sgte": 0,
	"NAB2016": 0,
	"E21": 0,
	"elrubiusfanart": 0,
	"jobsearch": 0,
	"RapeIsNotAJoke": 0,
	"trkLeash": 0,
	"foro": 0,
	"RAWLondon": 0,
	"NYPrimary2016": 0,
	"LesserRedpoll": 0,
	"wijn": 0,
	"TEAMDIAMANTE": 0,
	"FreeBiafra": 0,
	"ColbyKeller": 0,
	"douga": 0,
	"PurposeTourAtlanta": 0,
	"ndnl": 0,
	"FWCulturalDistrict": 0,
	"DolceAmoreLucianaAndDodong": 0,
	"Hillary": 0,
	"vikram": 0,
	"DUELEELCORAZON": 0,
	"BlackberryClassicSleeve": 0,
	"DUnever": 0,
	"EnginAkyürek": 0,
	"ott": 0,
	"Indiedev": 0,
	"ballet": 0,
	"twimaker": 0,
	"Stoner": 0,
	"PAPrimary": 0,
	"TeamKindaFunny": 0,
	"ComingSoon": 0,
	"OklahomaCity": 0,
	"wnn7": 0,
	"Game": 0,
	"Calumers": 0,
	"NairobiDiaries": 0,
	"feelsbadman": 0,
	"pulitzerprize": 0,
	"ccme16": 0,
	"KamdelaFu": 0,
	"QPOC": 0,
	"MiAmorDeLasEstrellas": 0,
	"hmrecipes": 0,
	"vsco": 0,
	"Communication": 0,
	"StanleyCup": 0,
	"sm20866443": 0,
	"EnDirect": 0,
	"DAY6": 0,
	"papillon": 0,
	"shsuadpi": 0,
	"diy": 0,
	"Noir": 0,
	"MusicMonday": 0,
	"spring": 0,
	"God": 0,
	"dajare": 0,
	"Kilis": 0,
	"towerdefense": 0,
	"GHVIPdirecto": 0,
	"CTPrimary": 0,
	"followme": 0,
	"Capitals": 0,
	"Delicias": 0,
	"MakeAmericaGreatAgain": 0,
	"EuroMillions": 0,
	"Jesus_Christ": 0,
	"selenawho": 0,
	"Anticipate": 0,
	"IOctane": 0,
	"EzidisForTrump": 0,
	"foificandoserio": 0,
	"toyota": 0,
	"Listen": 0,
	"smutwitterfam": 0,
	"NeverCruz": 0,
	"CursedChild": 0,
	"homeservices": 0,
	"CenadelleBeffe": 0,
	"OL": 0,
	"GetSTOKed": 0,
	"HarborLife": 0,
	"manifold": 0,
	"HappyAreumDay": 0,
	"CampoOnline": 0,
	"SaturdayNight": 0,
	"art": 0,
	"dorsethour": 0,
	"nyc": 0,
	"SpiderManHomecoming": 0,
	"GOT7": 0,
	"BB": 0,
	"lifestyle": 0,
	"MotivationMonday": 0,
	"JK": 0,
	"FortWorth": 0,
	"SismoEc": 0,
	"Expressen": 0,
	"BookBoost": 0,
	"UnitedKingdom": 0,
	"Nwkwesucceed": 0,
	"WIN": 0,
	"yoincluyoPcD": 0,
	"alrasyid448ItuRasya": 0,
	"getcreative": 0,
	"mPLUSPlaces": 0,
	"abilitatiTfa": 0,
	"RUSH": 0,
	"NCAT": 0,
	"lincshour": 0,
	"ebsscf": 0,
	"NadieImpediráTuFinalNico": 0,
	"TEAM1DIANA": 0,
	"AngieYNicoPionerosHastaElFinal": 0,
	"Nostananoshow": 0,
	"GOTV": 0,
	"meroerroretecnico": 0,
	"RAPMONSTER": 0,
	"vscocam": 0,
	"teamjayda": 0,
	"TPP": 0,
	"yuyushiki": 0,
	"YeahThisIsTheLove": 0,
	"FirstNameLastName": 0,
	"friendship": 0,
	"Geissens": 0,
	"garden": 0,
	"Bluetooth": 0,
	"AProscrire": 0,
	"sweeps": 1,
	"beauty": 1,
	"vansoffthewall": 1,
	"MaryamRajavi": 1,
	"OpExposeCPS": 1,
	"semáforoeconómico": 1,
	"Nottingham": 1,
	"health": 1,
	"iOS9": 1,
	"Syrie": 1,
	"earthquake": 1,
	"instgood": 1,
	"bestbelievethat": 1,
	"Iran": 1,
	"SCOTUS": 1,
	"DreamBig": 1,
	"Madrid": 1,
	"SLRG": 1,
	"fcblive": 1,
	"SOSTalento": 1,
	"nudegirls": 1,
	"Karaoke": 1,
	"np": 1,
	"ledigajobb": 1,
	"Amazon": 1,
	"sony": 1,
	"H3Journalism": 1,
	"FiguraRiver": 1,
	"TrumpTrain": 1,
	"blogginggals": 1,
	"TotalBellas": 1,
	"TerremotoEcuador": 1,
	"film": 1,
	"worcestershirehour": 1,
	"PymesUnidas": 1,
	"soilweek": 1,
	"CdnAg": 1,
	"Deals": 1,
	"writersblock": 1,
	"MagicalKenya": 1,
	"JurassicWorld2": 1,
	"Carpool": 1,
	"Tea4TheQueen": 1,
	"giveaway": 1,
	"filmmaking": 1,
	"bmrtg": 1,
	"SLFLNewcastle": 1,
	"content": 1,
	"businessevent": 1,
	"SayHeyToBoux": 1,
	"rockthered": 1,
	"offcampus": 1,
	"EI": 1,
	"18Abril": 1,
	"KuisJP": 1,
	"martyrs": 1,
	"MTVScream": 1,
	"nuboso": 1,
	"ListenLive": 1,
	"nieve": 1,
	"ALTER90S": 1,
	"NowWatching": 1,
	"BattleCreek": 1,
	"TodosSomosEcuador": 1,
	"FF": 1,
	"montaña": 1,
	"DangerousWoman": 1,
	"HillaryStrong": 1,
	"sabatino": 1,
	"Survivor": 1,
	"cats": 1,
	"grillin": 1,
	"iphone": 1,
	"BuyLetMeLoveYouOniTunes": 1,
	"BillAllen": 1,
	"JoaquinTodasMias": 1,
	"soil": 1,
	"nascarpics": 1,
	"otoño": 1,
	"LauriesIDPChallenge": 1,
	"salvadocerinza": 1,
	"someoneyoulove": 1,
	"ChampionshipOffseason": 1,
	"MiraQueEsBonita": 1,
	"ProjectHome": 1,
	"NFLDraft": 1,
	"OremosporEcuador": 1,
	"Habitat3": 1,
	"EcuadorEarthquake": 1,
	"jakolbagets": 1,
	"sexy": 1,
	"RETWEET": 1,
	"PymeEspaña": 1,
	"Isibaya": 1,
	"hobiecat16": 1,
	"lewinning": 1,
	"hobiecat15": 1,
	"nubes": 1,
	"SothebysPrints": 1,
	"pornostar": 1,
	"MovieAwards": 1,
	"FRASESBUNBURY": 1,
	"fastfood": 1,
	"blonde": 1,
	"tech": 1,
	"baget": 1,
	"placement": 1,
	"Ecuador": 1,
	"jakolna": 1,
	"MAGA": 1,
	"kaizerchiefs": 1,
	"Tortura": 1,
	"HoustonFloods": 1,
	"BEZ16": 1,
	"coding": 1,
	"TheAgenda": 1,
	"AAInforma": 1,
	"BAP": 1,
	"Commadue": 1,
	"London": 1,
	"gefeliciteerd": 1,
	"WorcestershireHour": 1,
	"Fashion": 1,
	"UnPaísDeFuturo": 1,
	"Capricornio": 1,
	"Independência": 1,
	"analytics": 1,
	"CuidadoComOAnjo101": 1,
	"ibtissamtiskat": 1,
	"formulahtv": 1,
	"gm2012infanzia": 1,
	"Apple": 1,
	"AdoptCat": 1,
	"prom_ua": 1,
	"amwriting": 1,
	"LaPAHalPP": 1,
	"Syria": 1,
	"amateur": 1,
	"sarapngbata": 1,
	"UFC197": 1,
	"AutoAccident": 1,
	"muerteasegurá": 1,
	"THE8": 1,
	"nieva": 1,
	"DennisHastert": 1,
	"Attorney": 1,
	"sphero": 1,
	"hobicat": 1,
	"StyleOnPicture": 1,
	"nytimes": 1,
	"nascar": 1,
	"montañas": 1,
	"MeColegio": 1,
	"NYC": 1,
	"movieTitlesGenerator": 1,
	"secrettolife": 1,
	"camera": 1,
	"xxx": 1,
	"k9hour": 1,
	"Earthquake": 1,
	"sex": 1,
	"porno": 1,
	"intensivo": 1,
	"phthalates": 1,
	"instal": 1,
	"NP": 1,
	"Adele": 1,
	"WeLoveSemarang": 1,
	"capspride": 1,
	"Beauty": 1,
	"NoHearingsNoVotes": 1,
	"YaNoMax": 1,
	"RaboDePaja": 1,
	"LeerEsVolar": 1,
	"fml": 1,
	"LosTela": 1,
	"truth": 1,
	"gmg": 1,
	"Realestate": 1,
	"follow": 1,
	"MiVoto40PabloLopez": 1,
	"cielo": 1,
	"finoallultimoidoneo": 1,
	"FantasticBeasts": 1,
	"SP17": 1,
	"Books": 1,
	"curso": 1,
	"me": 1,
	"feedly": 1,
	"sesverkadro": 1,
	"SLEEK": 1,
	"NoTePasesDeRosca": 1,
	"primerolasgafas": 1,
	"TengaTantitaMadre": 1,
	"basico": 1,
	"FDE2016": 1,
	"monsdansa": 1,
	"iPhone": 1,
	"IshratFile": 1,
	"Lifestyle": 1,
	"ML09Purple": 1,
	"AtlanticCity": 1,
	"ECDD": 1,
	"Adopt": 1,
	"CHP": 1,
	"Copenhagen": 1,
	"lluvias": 1,
	"SegundaDetremuraSdv": 1,
	"Tuskegee_RYS16": 1,
	"hotranking": 1,
	"LOEINLA": 1,
	"Blogger": 1,
	"Pedernales": 1,
	"LOE2016": 1,
	"paisaje": 1,
	"LaHoraChachi103": 1,
	"sarapngpinoy": 1,
	"Aquarius": 1,
	"powerof60": 1,
	"TweetMag1c": 1,
	"Câncer": 1,
	"ABC": 1,
	"skincare": 1,
	"lluvia": 1,
	"Homs": 1,
	"ArrestSultaniAndZia": 1,
	"politics": 1,
	"Orlando": 1,
	"GH": 1,
	"music": 1,
	"HealthCare": 1,
	"HereIAm": 1,
	"avataratakan": 1,
	"walkin": 1,
	"discapacidad": 1,
	"TFW": 1,
	"hardcore": 1,
	"iphonegames": 1,
	"SmashAfterlife": 1,
	"a2ilta": 1,
	"Virgem": 1,
	"AACC": 1,
	"souhilaBenlachhab": 1,
	"hobiecat14": 1,
	"PavelNuneez_": 1,
	"FFH": 1,
	"ComeAtMeBro": 1,
	"OpExposeCPSAZ": 1,
	"seiallalberghiero": 1,
	"FREE": 1,
	"batangmalibog": 1,
	"DolarFuturo": 1,
	"Insurance": 2,
	"BeSouthern": 2,
	"asugsvsummit": 2,
	"NationalParkWeek": 2,
	"WoopGang": 2,
	"EcuadorListoYSolidario": 2,
	"healthy": 2,
	"Rap": 2,
	"WinstonSalem": 2,
	"BattleOfNewYork": 2,
	"Bernie2016": 2,
	"asses": 2,
	"squirt": 2,
	"hannity": 2,
	"SMMW16": 2,
	"married": 2,
	"Vucic": 2,
	"Jobs": 2,
	"QueVuelvaElMcRib": 2,
	"YoVoyConLaPAH": 2,
	"TuitUtil": 2,
	"SavedAClick": 2,
	"CSGO": 2,
	"SabíasQue": 2,
	"Jerusalem": 2,
	"butt": 2,
	"Content": 2,
	"Blues": 2,
	"ZaynMalik": 2,
	"orgasm": 2,
	"greatdanetakeover": 2,
	"AreYouReady": 2,
	"LWSA16": 2,
	"OtegiSalvadosARV": 2,
	"Aries": 2,
	"DolceAmoreChallenge": 2,
	"Brilliant": 2,
	"Gemini": 2,
	"PAprimary": 2,
	"Devon": 2,
	"CareerArc": 2,
	"DevOps": 2,
	"Diets": 2,
	"beadedbliss": 2,
	"Bloggers4Bernie": 2,
	"BerNY": 2,
	"sm26976762": 2,
	"wife": 2,
	"CruzCrew": 2,
	"CAPRICORNIO": 2,
	"Caracas": 2,
	"CALCETA": 2,
	"ElPerdedor": 2,
	"TheForceAwakens": 2,
	"soyturquesa": 2,
	"igot7selcaday": 2,
	"DHTGiPhoneSE": 2,
	"LISSD": 2,
	"ilovehim": 2,
	"manbun": 2,
	"JAMA": 2,
	"earring": 2,
	"baekhyun": 2,
	"love": 2,
	"OrgulloPoblano": 2,
	"FREETHEDICK": 2,
	"dreambig": 2,
	"MotoresProducti": 2,
	"photography": 2,
	"TheGuardian": 2,
	"BuenaNoticia": 2,
	"FandomFriday": 2,
	"BuffyTheVampireSlayer": 2,
	"Requirements": 2,
	"affair": 2,
	"nowplaying": 2,
	"SANVICENTE": 2,
	"Mixtape": 2,
	"DirtySouth": 2,
	"JustinBieber": 2,
	"MindOfMine": 2,
	"Intervju": 2,
	"DemiLovato": 2,
	"BTS": 2,
	"DigitalTransformation": 2,
	"RiseUp": 2,
	"GOTVForBernie": 2,
	"gatheringsfloralstudio": 2,
	"krishnadasi": 2,
	"WestCoast": 2,
	"EspecialCombate": 2,
	"ConsultaPodemosARV": 2,
	"sonoannichetiaspetto": 2,
	"hiring": 2,
	"TopEuropaTeEscucha": 2,
	"BuenasTareasPuntoCom": 2,
	"Abailartour": 2,
	"Storage": 2,
	"necklace": 2,
	"dating": 2,
	"VoteTrump": 2,
	"BigData": 2,
	"hartaberfair": 2,
	"motionmusic": 2,
	"mqn": 2,
	"HappyHour": 2,
	"Gangsta": 2,
	"CustomerService": 2,
	"IOGodfrey": 2,
	"WeightLoss": 2,
	"G1": 2,
	"ElDeliveryResponsable": 2,
	"SiMiriamAngSagot": 2,
	"KOBE": 2,
	"Trump2016": 2,
	"bnsscf": 2,
	"CivilWar": 2,
	"IoT": 2,
	"NoALaDroga": 2,
	"WWELondon": 2,
	"Health": 2,
	"libra": 2,
	"ArianaGrande": 2,
	"MarianYBrianAlBailando": 2,
	"houstonflood": 2,
	"HealNOTHeel": 2,
	"TheNiceGuys": 2,
	"tekirdagtravesti": 3,
	"alto2016": 3,
	"GetAllJobs": 3,
	"videos": 3,
	"TreCru": 3,
	"cerkezkoytravesti": 3,
	"ukclique": 3,
	"bead": 3,
	"teen": 3,
	"catalcatravesti": 3,
	"Chone": 3,
	"nicoseiga": 3,
	"egzamingimnazjalny": 3,
	"MondayMotivation": 3,
	"Cloud": 3,
	"porn": 3,
	"winning": 3,
	"TaxDay": 3,
	"Kenner": 3,
	"Al_Hakura": 3,
	"Áries": 3,
	"DesaparecidosEC": 3,
	"FREESHAKE": 3,
	"batman": 3,
	"technology": 3,
	"Tuesday": 3,
	"AHLIFC": 3,
	"TeamIronMan": 3,
	"motavatormonday": 3,
	"andbead": 3,
	"future": 3,
	"gemstone": 3,
	"Castle": 3,
	"RHOH": 3,
	"beads": 3,
	"SUGA": 3,
	"business": 3,
	"TechnicalSupport": 3,
	"inu": 3,
	"im5731719": 3,
	"KINDLE": 3,
	"crazy": 3,
	"TheMurexDor_IbtissamTiskat": 3,
	"MBC1": 3,
	"BeerMe": 3,
	"maigo": 3,
	"Corlutravesti": 3,
	"silivritravesti": 3,
	"youtube": 3,
	"BigWeekend": 3,
	"dog": 3,
	"CSent": 3,
	"mondaymotivation": 3,
	"SanJose": 3,
	"mmda": 3,
	"buyukcekmecetravesti": 3,
	"Legend": 3,
	"ÜmitVar": 4,
	"ComandoAs": 4,
	"NBLNathaliaVoto": 4,
	"retweetsy": 4,
	"NowPlaying": 4,
	"isoladiCARTA": 4,
	"jobs": 4,
	"nsfw": 4,
	"BostonMarathon": 4,
	"FCBnews": 4,
	"TimeNoDey": 4,
	"earrings": 4,
	"seo": 4,
	"Job": 4,
	"BlancaSeFueEnBlanco": 4,
	"web2": 4,
	"etsymntt": 4,
	"winehousevoice": 4,
	"FeelTheBern": 5,
	"NYPrimary": 5,
	"Allin": 5,
	"android": 5,
	"Hiring": 5,
	"HT30SecondCover": 5,
	"androidgames": 5,
	"H3Toluca": 5,
	"ALDUBActing101": 6,
	"JJDollarSubDay": 6,
	"tl": 6,
	"isola": 6,
	"DataCenter": 6,
	"1MDeCorazonesATuLadoMichi": 6,
	"Periscope": 7,
	"ElNiñoNoEsJuego": 7,
	"job": 9,
	"FelizLunes": 9,
	"gameinsight": 9,
	"RT": 10,
	"BigAppleMusicAwardsBestSocialMediaStar2016_IbtissamTiskat": 10,
	"BAMA2016PlatinumEdition_IbtissamTiskat": 10,
	"MSGthoughts": 10,
	"Pulitzer100": 11
}